amazing_printer/__init__.py
amazing_printer/colorize.py
amazing_printer/formatter.py
amazing_printer/indentator.py
amazing_printer/inspector.py
amazing_printer/formatters/__init__.py
amazing_printer/formatters/base_formatter.py
amazing_printer/formatters/dict_formatter.py
amazing_printer/formatters/list_formatter.py
amazing_printer/formatters/object_formatter.py
amazing_printer/formatters/ordered_dict_formatter.py
amazing_printer/formatters/set_formatter.py
amazing_printer/formatters/simple_formatter.py
amazing_printer/formatters/tuple_formatter.py
amazing_printer/tests/__init__.py
amazing_printer/tests/test_formatter.py
amazing_printer/tests/test_indentator.py
amazing_printer/tests/test_inspector.py
amazing_printer-0.1.0.dist-info/LICENSE
amazing_printer-0.1.0.dist-info/METADATA
amazing_printer-0.1.0.dist-info/WHEEL
amazing_printer-0.1.0.dist-info/top_level.txt
amazing_printer-0.1.0.dist-info/RECORD
