Metadata-Version: 2.1
Name: amazing-printer
Version: 0.1.0
Summary: A python package that pretty prints Python objects with colors and proper indentation.
Home-page: https://github.com/tkbky/amazing_printer
Author: Kher Yee, Ting
Author-email: infcurious@gmail.com
License: UNKNOWN
Platform: UNKNOWN
Classifier: Programming Language :: Python :: 3
Classifier: License :: OSI Approved :: MIT License
Classifier: Operating System :: OS Independent
Requires-Dist: colorama (>=0.4.0)
